docstruct/__init__.py
docstruct/affine_transformations.py
docstruct/bounding_box.py
docstruct/constants.py
docstruct/drawer.py
docstruct/equalizer.py
docstruct/graph.py
docstruct/hocr_parser.py
docstruct/ligatures.py
docstruct/page_alignment.py
docstruct/page_creator.py
docstruct/point.py
docstruct/searchable_pdf.py
docstruct/segment.py
docstruct/space_partitioning.py
docstruct/spatial_grid_indexing.py
docstruct/text_block.py
docstruct/text_block_splitter.py
docstruct/textract_parser.py
docstruct/utils.py
docstruct/version.py
docstruct/vis_line.py
docstruct/paragraph_detection/__init__.py
docstruct/paragraph_detection/constants.py
docstruct/paragraph_detection/paragraph_extractor.py
docstruct/paragraph_detection/paragraph_sorter.py
docstruct/paragraph_detection/two_columns.py
docstruct/serializer/__init__.py
docstruct/serializer/constants.py
docstruct/serializer/json_serializer.py
docstruct/visual_detection/__init__.py
docstruct/visual_detection/bordered_table_extraction.py
docstruct/visual_detection/constants.py
docstruct/visual_detection/table_extraction.py
docstruct/visual_detection/utils.py
docstruct/visual_detection/vis_line.py
docstruct/visual_detection/vis_line_detection.py
docstruct-1.0.251.dist-info/LICENSE.txt
docstruct-1.0.251.dist-info/METADATA
docstruct-1.0.251.dist-info/WHEEL
docstruct-1.0.251.dist-info/top_level.txt
docstruct-1.0.251.dist-info/RECORD
