Metadata-Version: 2.1
Name: docstruct
Version: 1.0.251
Summary: A package for representing documents as a tree of document, pages, paragraphs, lines, words, and characters
Home-page: https://github.com/smrt-co/docstruct
Author: Moran Nechushtan, Serah Tapia, Shlomo Agishtein
Author-email: moran.n@trullion.com, serah@trullion.com, shlomo@trullion.com
Classifier: Programming Language :: Python :: 3
Classifier: Operating System :: OS Independent
License-File: LICENSE.txt
Requires-Dist: attrs (>=22.0.0)
Requires-Dist: pillow (>=8.1.1)
Requires-Dist: numpy (==1.23.2)
Requires-Dist: openpyxl (==3.1.2)
